{
  "layout":{
    "children":[
      {
        "cls":"feathers.display.Scale3Image",
        "constructorParams":[
          {
            "cls":"feathers.textures.Scale3Textures",
            "scaleRatio":[
              0.28,
              0.3,
              "vertical"
            ],
            "textureName":"generic_popup_bg"
          }
        ],
        "customParams":{},
        "params":{
          "height":645,
          "name":"generic_popup_bg",
          "width":638,
          "x":-1.5,
          "y":51
        }
      },
      {
        "cls":"starling.display.Button",
        "constructorParams":[
          {
            "cls":"starling.textures.Texture",
            "textureName":"generic_exit"
          }
        ],
        "customParams":{},
        "params":{
          "height":74,
          "name":"generic_exit",
          "width":77,
          "x":559.5,
          "y":41
        }
      },
      {
        "cls":"starling.display.Image",
        "constructorParams":[
          {
            "cls":"starling.textures.Texture",
            "textureName":"title_bg"
          }
        ],
        "customParams":{},
        "params":{
          "height":85,
          "name":"title_bg",
          "width":419,
          "x":108,
          "y":16.5
        }
      },
      {
        "cls":"starling.text.TextField",
        "constructorParams":[
          {
            "value":200
          },
          {
            "value":100
          },
          {
            "value":"Abc123"
          },
          {
            "value":"Verdana"
          },
          {
            "value":46
          },
          {
            "value":16777215
          }
        ],
        "customParams":{},
        "params":{
          "autoSize":"bothDirections",
          "fontName":"LobsterTwoRegular_Size54_ColorFFFFFF_StrokeAF384E_DropShadow560D1B",
          "fontSize":55,
          "height":58.05555555555557,
          "name":"LobsterTwoRegular_Size54_ColorFFFFFF_StrokeAF384E_DropShadow560D1B",
          "text":"Inbox",
          "width":135.462962962963,
          "x":249.7685185185186,
          "y":36
        }
      },
      {
        "cls":"feathers.controls.List",
        "customParams":{},
        "params":{
          "height":515,
          "name":"obj1",
          "width":534,
          "x":54.500000000000114,
          "y":122
        }
      }
    ],
    "cls":"starling.display.Sprite",
    "customParams":{
      "container":1
    },
    "params":{
      "name":null
    }
  },
  "setting":{
    "canvasSize":{
      "x":640,
      "y":860
    }
  },
  "version":"1.0"
}